pic_to_header/__init__.py
pic_to_header/app.py
pic_to_header/cli.py
pic_to_header/core.py
tests/__init__.py
tests/test_core.py
pic_to_header-0.1.1.dist-info/LICENSE
pic_to_header-0.1.1.dist-info/METADATA
pic_to_header-0.1.1.dist-info/WHEEL
pic_to_header-0.1.1.dist-info/entry_points.txt
pic_to_header-0.1.1.dist-info/top_level.txt
pic_to_header-0.1.1.dist-info/RECORD
