Metadata-Version: 2.1
Name: pic-to-header
Version: 0.1.1
Summary: A Python application to generate header images using mask and input images
Home-page: https://github.com/Sunwood-ai-labs/pic-to-header
Author: Sunwood-ai-labs
Author-email: your.email@example.com
Classifier: Development Status :: 3 - Alpha
Classifier: Intended Audience :: Developers
Classifier: License :: OSI Approved :: MIT License
Classifier: Operating System :: OS Independent
Classifier: Programming Language :: Python :: 3
Classifier: Programming Language :: Python :: 3.7
Classifier: Programming Language :: Python :: 3.8
Classifier: Programming Language :: Python :: 3.9
Requires-Python: >=3.7
License-File: LICENSE
Requires-Dist: streamlit
Requires-Dist: opencv-python
Requires-Dist: numpy
Requires-Dist: loguru
